django_hawk_drf/__init__.py
django_hawk_drf/authentication.py
django_hawk_drf/middleware.py
django_hawk_drf/py.typed
django_hawk_drf/tests/__init__.py
django_hawk_drf/tests/settings.py
django_hawk_drf/tests/test_views.py
django_hawk_drf/tests/test_views_drf.py
django_hawk_drf/tests/urls.py
django_hawk_drf/tests/views.py
django_hawk_drf-1.1.5.dist-info/LICENSE
django_hawk_drf-1.1.5.dist-info/METADATA
django_hawk_drf-1.1.5.dist-info/WHEEL
django_hawk_drf-1.1.5.dist-info/RECORD
