Metadata-Version: 2.1
Name: django-hawk-drf
Version: 1.1.5
Summary: Authenticate Django Rest Framework Views with django-hawk
Home-page: https://github.com/uktrade/django-hawk-drf/
License: MIT
Keywords: django
Author: Cameron Lamb
Author-email: live.services@digital.trade.gov.uk
Requires-Python: >=3.8,<4.0
Classifier: License :: OSI Approved :: MIT License
Classifier: Programming Language :: Python :: 3
Classifier: Programming Language :: Python :: 3.8
Classifier: Programming Language :: Python :: 3.9
Classifier: Programming Language :: Python :: 3.10
Classifier: Programming Language :: Python :: 3.11
Classifier: Programming Language :: Python :: 3.12
Requires-Dist: Django (>=4.2,<6)
Requires-Dist: django-hawk (>=1.2.3,<2.0.0)
Requires-Dist: djangorestframework (>=3.10.3,<4.0)
